CHANGES.txt
CONTRIBUTORS.txt
MANIFEST.in
MIT-LICENSE.txt
README.md
setup.py
DjScript.egg-info/PKG-INFO
DjScript.egg-info/SOURCES.txt
DjScript.egg-info/dependency_links.txt
DjScript.egg-info/requires.txt
DjScript.egg-info/top_level.txt
djscript/__init__.py
djscript/utils.py