Metadata-Version: 1.0
Name: DjScript
Version: 0.1.0
Summary: Django package for using the RapydScript javascript compiler
Home-page: https://github.com/pztrick/djscript/
Author: Patrick Paul
Author-email: pztrick44@gmail.com
License: MIT-LICENSE.txt
Platform: UNKNOWN
